twrpdtgen/__init__.py
twrpdtgen/__main__.py
twrpdtgen/device_tree.py
twrpdtgen/main.py
twrpdtgen/templates/Android.bp.jinja2
twrpdtgen/templates/Android.mk.jinja2
twrpdtgen/templates/AndroidProducts.mk.jinja2
twrpdtgen/templates/BoardConfig.mk.jinja2
twrpdtgen/templates/LICENSE.jinja2
twrpdtgen/templates/README.md.jinja2
twrpdtgen/templates/__init__.py
twrpdtgen/templates/commit_message.jinja2
twrpdtgen/templates/device.mk.jinja2
twrpdtgen/templates/extract-files.sh.jinja2
twrpdtgen/templates/omni_device.mk.jinja2
twrpdtgen/templates/setup-makefiles.sh.jinja2
twrpdtgen/templates/vendorsetup.sh.jinja2
twrpdtgen/utils/device_info.py
twrpdtgen/utils/template.py
twrpdtgen-3.0.0.dist-info/WHEEL
twrpdtgen-3.0.0.dist-info/METADATA
twrpdtgen-3.0.0.dist-info/RECORD
