Metadata-Version: 2.1
Name: twrpdtgen
Version: 3.0.0
Summary: A Python library/script to automatically generate TWRP-compatible device tree from a boot/recovery image
Home-page: https://github.com/twrpdtgen/twrpdtgen
License: Apache-2.0
Author: Sebastiano Barezzi
Author-email: barezzisebastiano@gmail.com
Requires-Python: >=3.8,<4.0
Classifier: License :: OSI Approved :: Apache Software License
Classifier: Programming Language :: Python :: 3
Classifier: Programming Language :: Python :: 3.8
Classifier: Programming Language :: Python :: 3.9
Classifier: Programming Language :: Python :: 3.10
Requires-Dist: GitPython (>=3.1.27,<4.0.0)
Requires-Dist: Jinja2 (>=3.1.1,<4.0.0)
Requires-Dist: sebaubuntu-libs (>=1.3.0,<2.0.0)
Project-URL: Repository, https://github.com/twrpdtgen/twrpdtgen
